setuptools_py2cfg.py
setuptools_py2cfg-2.1.0.dist-info/LICENSE
setuptools_py2cfg-2.1.0.dist-info/METADATA
setuptools_py2cfg-2.1.0.dist-info/WHEEL
setuptools_py2cfg-2.1.0.dist-info/entry_points.txt
setuptools_py2cfg-2.1.0.dist-info/top_level.txt
setuptools_py2cfg-2.1.0.dist-info/RECORD
