Metadata-Version: 2.1
Name: setuptools-py2cfg
Version: 2.1.0
Summary: Converts a setuptools setup.py to setup.cfg
Author-email: Georgi Valkov <georgi.t.valkov@gmail.com>
License: Revised BSD License
Project-URL: Homepage, https://github.com/gvalkov/setuptools-py2cfg
Keywords: setuptools,setup.cfg
Classifier: Development Status :: 5 - Production/Stable
Classifier: Programming Language :: Python :: 3
Classifier: Intended Audience :: Developers
Classifier: License :: OSI Approved :: BSD License
Requires-Python: >=3.6
License-File: LICENSE
Requires-Dist: setuptools ; python_version >= "3.12"
Provides-Extra: test
Requires-Dist: pytest ; extra == 'test'
